[{"keyword": "연구", "score": 5072, "cooccur": [{"index": 1, "subkeyword": "팀", "cooccur_num": 739}, {"index": 2, "subkeyword": "교수", "cooccur_num": 483}, {"index": 3, "subkeyword": "개발", "cooccur_num": 435}, {"index": 4, "subkeyword": "센터", "cooccur_num": 356}, {"index": 5, "subkeyword": "기술", "cooccur_num": 328}, {"index": 6, "subkeyword": "분야", "cooccur_num": 318}, {"index": 7, "subkeyword": "결과", "cooccur_num": 294}, {"index": 8, "subkeyword": "공동", "cooccur_num": 264}, {"index": 9, "subkeyword": "대학", "cooccur_num": 241}, {"index": 10, "subkeyword": "성과", "cooccur_num": 225}], "similar": [{"index": 1, "subkeyword": "면역학", "cooccur_num": 0.7480086088180542}, {"index": 2, "subkeyword": "저작", "cooccur_num": 0.7440983653068542}, {"index": 3, "subkeyword": "김봉수", "cooccur_num": 0.7343518733978271}, {"index": 4, "subkeyword": "팹", "cooccur_num": 0.7321634292602539}, {"index": 5, "subkeyword": "기초과학", "cooccur_num": 0.7275056838989258}, {"index": 6, "subkeyword": "나노", "cooccur_num": 0.7226868867874146}, {"index": 7, "subkeyword": "생물학", "cooccur_num": 0.7154206037521362}, {"index": 8, "subkeyword": "연구실", "cooccur_num": 0.7148370742797852}, {"index": 9, "subkeyword": "게재", "cooccur_num": 0.7124767303466797}, {"index": 10, "subkeyword": "박주용", "cooccur_num": 0.7118138074874878}]}, {"keyword": "기술", "score": 4047, "cooccur": [{"index": 1, "subkeyword": "개발", "cooccur_num": 886}, {"index": 2, "subkeyword": "연구", "cooccur_num": 329}, {"index": 3, "subkeyword": "한국", "cooccur_num": 226}, {"index": 4, "subkeyword": "교수", "cooccur_num": 182}, {"index": 5, "subkeyword": "산업", "cooccur_num": 181}, {"index": 6, "subkeyword": "분야", "cooccur_num": 160}, {"index": 7, "subkeyword": "연구원", "cooccur_num": 139}, {"index": 8, "subkeyword": "국내", "cooccur_num": 132}, {"index": 9, "subkeyword": "사업", "cooccur_num": 128}, {"index": 10, "subkeyword": "첨단", "cooccur_num": 127}], "similar": [{"index": 1, "subkeyword": "인공지능", "cooccur_num": 0.9146201610565186}, {"index": 2, "subkeyword": "반도체", "cooccur_num": 0.912783145904541}, {"index": 3, "subkeyword": "원천", "cooccur_num": 0.9125959873199463}, {"index": 4, "subkeyword": "소프트웨어", "cooccur_num": 0.9028743505477905}, {"index": 5, "subkeyword": "첨단", "cooccur_num": 0.9012886881828308}, {"index": 6, "subkeyword": "응용", "cooccur_num": 0.8988599181175232}, {"index": 7, "subkeyword": "인간공학", "cooccur_num": 0.8935829997062683}, {"index": 8, "subkeyword": "시스템", "cooccur_num": 0.8888182640075684}, {"index": 9, "subkeyword": "통신", "cooccur_num": 0.888705849647522}, {"index": 10, "subkeyword": "부품", "cooccur_num": 0.8871307373046875}]}, {"keyword": "한국", "score": 3750, "cooccur": [{"index": 1, "subkeyword": "연구원", "cooccur_num": 701}, {"index": 2, "subkeyword": "과학기술", "cooccur_num": 307}, {"index": 3, "subkeyword": "과학", "cooccur_num": 244}, {"index": 4, "subkeyword": "교수", "cooccur_num": 242}, {"index": 5, "subkeyword": "기술", "cooccur_num": 223}, {"index": 6, "subkeyword": "연구", "cooccur_num": 183}, {"index": 7, "subkeyword": "서울", "cooccur_num": 158}, {"index": 8, "subkeyword": "대학", "cooccur_num": 158}, {"index": 9, "subkeyword": "원", "cooccur_num": 135}, {"index": 10, "subkeyword": "장", "cooccur_num": 130}], "similar": [{"index": 1, "subkeyword": "전자통신", "cooccur_num": 0.809215784072876}, {"index": 2, "subkeyword": "협회", "cooccur_num": 0.8068270683288574}, {"index": 3, "subkeyword": "항공우주", "cooccur_num": 0.7979779243469238}, {"index": 4, "subkeyword": "페임", "cooccur_num": 0.7965946197509766}, {"index": 5, "subkeyword": "김은영", "cooccur_num": 0.7962266206741333}, {"index": 6, "subkeyword": "서정욱", "cooccur_num": 0.792650580406189}, {"index": 7, "subkeyword": "원자력", "cooccur_num": 0.7909842729568481}, {"index": 8, "subkeyword": "한림원", "cooccur_num": 0.7902292609214783}, {"index": 9, "subkeyword": "행정가", "cooccur_num": 0.7751831412315369}, {"index": 10, "subkeyword": "리켄", "cooccur_num": 0.7705593109130859}]}, {"keyword": "대학", "score": 3552, "cooccur": [{"index": 1, "subkeyword": "세계", "cooccur_num": 259}, {"index": 2, "subkeyword": "교수", "cooccur_num": 238}, {"index": 3, "subkeyword": "연구", "cooccur_num": 236}, {"index": 4, "subkeyword": "국내", "cooccur_num": 229}, {"index": 5, "subkeyword": "명", "cooccur_num": 191}, {"index": 6, "subkeyword": "학생", "cooccur_num": 184}, {"index": 7, "subkeyword": "카이스트", "cooccur_num": 172}, {"index": 8, "subkeyword": "한국", "cooccur_num": 167}, {"index": 9, "subkeyword": "지원", "cooccur_num": 166}, {"index": 10, "subkeyword": "들이다", "cooccur_num": 162}], "similar": [{"index": 1, "subkeyword": "이공계", "cooccur_num": 0.9081413745880127}, {"index": 2, "subkeyword": "외국", "cooccur_num": 0.8842756748199463}, {"index": 3, "subkeyword": "카이스트신문", "cooccur_num": 0.85643070936203}, {"index": 4, "subkeyword": "외국인", "cooccur_num": 0.8547216653823853}, {"index": 5, "subkeyword": "남이공", "cooccur_num": 0.8532158136367798}, {"index": 6, "subkeyword": "우수", "cooccur_num": 0.8525550365447998}, {"index": 7, "subkeyword": "대학평가", "cooccur_num": 0.850326418876648}, {"index": 8, "subkeyword": "사립대", "cooccur_num": 0.8426538705825806}, {"index": 9, "subkeyword": "국립대", "cooccur_num": 0.8355064392089844}, {"index": 10, "subkeyword": "명문", "cooccur_num": 0.831215500831604}]}, {"keyword": "개발", "score": 3221, "cooccur": [{"index": 1, "subkeyword": "기술", "cooccur_num": 898}, {"index": 2, "subkeyword": "연구", "cooccur_num": 421}, {"index": 3, "subkeyword": "밝히다", "cooccur_num": 194}, {"index": 4, "subkeyword": "팀", "cooccur_num": 168}, {"index": 5, "subkeyword": "카이스트", "cooccur_num": 144}, {"index": 6, "subkeyword": "교수", "cooccur_num": 140}, {"index": 7, "subkeyword": "치료", "cooccur_num": 139}, {"index": 8, "subkeyword": "사업", "cooccur_num": 131}, {"index": 9, "subkeyword": "국내", "cooccur_num": 127}, {"index": 10, "subkeyword": "세계", "cooccur_num": 125}], "similar": [{"index": 1, "subkeyword": "나노", "cooccur_num": 0.92423015832901}, {"index": 2, "subkeyword": "소재", "cooccur_num": 0.9024652242660522}, {"index": 3, "subkeyword": "플렉서블", "cooccur_num": 0.8932448625564575}, {"index": 4, "subkeyword": "신소재", "cooccur_num": 0.8898811340332031}, {"index": 5, "subkeyword": "반도체", "cooccur_num": 0.8860945701599121}, {"index": 6, "subkeyword": "응용", "cooccur_num": 0.8816452622413635}, {"index": 7, "subkeyword": "시스템", "cooccur_num": 0.8660467863082886}, {"index": 8, "subkeyword": "섬유", "cooccur_num": 0.8637267351150513}, {"index": 9, "subkeyword": "딥", "cooccur_num": 0.8627410531044006}, {"index": 10, "subkeyword": "장비", "cooccur_num": 0.8612859845161438}]}, {"keyword": "늘다", "score": 3120, "cooccur": [{"index": 1, "subkeyword": "교수", "cooccur_num": 132}, {"index": 2, "subkeyword": "연구", "cooccur_num": 113}, {"index": 3, "subkeyword": "대학", "cooccur_num": 96}, {"index": 4, "subkeyword": "요하", "cooccur_num": 91}, {"index": 5, "subkeyword": "나타", "cooccur_num": 90}, {"index": 6, "subkeyword": "세계", "cooccur_num": 85}, {"index": 7, "subkeyword": "오다", "cooccur_num": 85}, {"index": 8, "subkeyword": "기술", "cooccur_num": 81}, {"index": 9, "subkeyword": "학생", "cooccur_num": 81}, {"index": 10, "subkeyword": "명", "cooccur_num": 77}], "similar": [{"index": 1, "subkeyword": "지금", "cooccur_num": 0.8716051578521729}, {"index": 2, "subkeyword": "과학계", "cooccur_num": 0.8625287413597107}, {"index": 3, "subkeyword": "분명", "cooccur_num": 0.8560163974761963}, {"index": 4, "subkeyword": "아직", "cooccur_num": 0.851371169090271}, {"index": 5, "subkeyword": "갖다", "cooccur_num": 0.8495558500289917}, {"index": 6, "subkeyword": "우려", "cooccur_num": 0.8478586673736572}, {"index": 7, "subkeyword": "먼저", "cooccur_num": 0.8471513986587524}, {"index": 8, "subkeyword": "지지", "cooccur_num": 0.8407565355300903}, {"index": 9, "subkeyword": "떠밀다", "cooccur_num": 0.8392825126647949}, {"index": 10, "subkeyword": "다르다", "cooccur_num": 0.8392684459686279}]}, {"keyword": "카이스트", "score": 2944, "cooccur": [{"index": 1, "subkeyword": "교수", "cooccur_num": 718}, {"index": 2, "subkeyword": "총장", "cooccur_num": 224}, {"index": 3, "subkeyword": "연구", "cooccur_num": 206}, {"index": 4, "subkeyword": "서울", "cooccur_num": 179}, {"index": 5, "subkeyword": "서울대", "cooccur_num": 176}, {"index": 6, "subkeyword": "대학", "cooccur_num": 163}, {"index": 7, "subkeyword": "학생", "cooccur_num": 143}, {"index": 8, "subkeyword": "개발", "cooccur_num": 129}, {"index": 9, "subkeyword": "대학원", "cooccur_num": 123}, {"index": 10, "subkeyword": "신문", "cooccur_num": 119}], "similar": [{"index": 1, "subkeyword": "한국과학기술원", "cooccur_num": 0.8723809123039246}, {"index": 2, "subkeyword": "우운", "cooccur_num": 0.8716022968292236}, {"index": 3, "subkeyword": "정재승", "cooccur_num": 0.8532721400260925}, {"index": 4, "subkeyword": "신소재공학", "cooccur_num": 0.8154985904693604}, {"index": 5, "subkeyword": "신성철", "cooccur_num": 0.81524658203125}, {"index": 6, "subkeyword": "석좌교수", "cooccur_num": 0.8131681680679321}, {"index": 7, "subkeyword": "기계공학", "cooccur_num": 0.809093177318573}, {"index": 8, "subkeyword": "전산학", "cooccur_num": 0.8046078681945801}, {"index": 9, "subkeyword": "강성모", "cooccur_num": 0.8032627105712891}, {"index": 10, "subkeyword": "뇌공", "cooccur_num": 0.7972961664199829}]}, {"keyword": "들이다", "score": 2773, "cooccur": [{"index": 1, "subkeyword": "학생", "cooccur_num": 421}, {"index": 2, "subkeyword": "사람", "cooccur_num": 190}, {"index": 3, "subkeyword": "교수", "cooccur_num": 172}, {"index": 4, "subkeyword": "대학", "cooccur_num": 165}, {"index": 5, "subkeyword": "기업", "cooccur_num": 148}, {"index": 6, "subkeyword": "연구", "cooccur_num": 95}, {"index": 7, "subkeyword": "만들다", "cooccur_num": 80}, {"index": 8, "subkeyword": "전문가", "cooccur_num": 80}, {"index": 9, "subkeyword": "국내", "cooccur_num": 79}, {"index": 10, "subkeyword": "참여", "cooccur_num": 78}], "similar": [{"index": 1, "subkeyword": "키우다", "cooccur_num": 0.7833303809165955}, {"index": 2, "subkeyword": "가르치다", "cooccur_num": 0.741719126701355}, {"index": 3, "subkeyword": "대부분", "cooccur_num": 0.7380738854408264}, {"index": 4, "subkeyword": "꿈", "cooccur_num": 0.7378467917442322}, {"index": 5, "subkeyword": "외국인", "cooccur_num": 0.730174720287323}, {"index": 6, "subkeyword": "진로", "cooccur_num": 0.7299607992172241}, {"index": 7, "subkeyword": "특허법원", "cooccur_num": 0.7280811071395874}, {"index": 8, "subkeyword": "실력", "cooccur_num": 0.728034257888794}, {"index": 9, "subkeyword": "대학생", "cooccur_num": 0.7250961065292358}, {"index": 10, "subkeyword": "모으다", "cooccur_num": 0.7233902812004089}]}, {"keyword": "서울", "score": 2542, "cooccur": [{"index": 1, "subkeyword": "신문", "cooccur_num": 3649}, {"index": 2, "subkeyword": "씨", "cooccur_num": 536}, {"index": 3, "subkeyword": "오전", "cooccur_num": 506}, {"index": 4, "subkeyword": "발인", "cooccur_num": 489}, {"index": 5, "subkeyword": "병원", "cooccur_num": 311}, {"index": 6, "subkeyword": "삼성", "cooccur_num": 260}, {"index": 7, "subkeyword": "상", "cooccur_num": 245}, {"index": 8, "subkeyword": "아산병원", "cooccur_num": 244}, {"index": 9, "subkeyword": "교수", "cooccur_num": 209}, {"index": 10, "subkeyword": "카이스트", "cooccur_num": 173}], "similar": [{"index": 1, "subkeyword": "라이브러리", "cooccur_num": 0.873275101184845}, {"index": 2, "subkeyword": "매일경제", "cooccur_num": 0.8152940273284912}, {"index": 3, "subkeyword": "미카엘", "cooccur_num": 0.8007552623748779}, {"index": 4, "subkeyword": "황실", "cooccur_num": 0.7954623699188232}, {"index": 5, "subkeyword": "유림", "cooccur_num": 0.7772204875946045}, {"index": 6, "subkeyword": "회의실", "cooccur_num": 0.776320219039917}, {"index": 7, "subkeyword": "서귀포", "cooccur_num": 0.7749400734901428}, {"index": 8, "subkeyword": "청암", "cooccur_num": 0.7701511383056641}, {"index": 9, "subkeyword": "파이낸셜뉴스", "cooccur_num": 0.7688077688217163}, {"index": 10, "subkeyword": "공원", "cooccur_num": 0.7644442319869995}]}, {"keyword": "학생", "score": 2540, "cooccur": [{"index": 1, "subkeyword": "들이다", "cooccur_num": 424}, {"index": 2, "subkeyword": "교수", "cooccur_num": 232}, {"index": 3, "subkeyword": "명", "cooccur_num": 196}, {"index": 4, "subkeyword": "대학", "cooccur_num": 189}, {"index": 5, "subkeyword": "학교", "cooccur_num": 158}, {"index": 6, "subkeyword": "카이스트", "cooccur_num": 146}, {"index": 7, "subkeyword": "교육", "cooccur_num": 108}, {"index": 8, "subkeyword": "총장", "cooccur_num": 91}, {"index": 9, "subkeyword": "자살", "cooccur_num": 90}, {"index": 10, "subkeyword": "우수", "cooccur_num": 89}], "similar": [{"index": 1, "subkeyword": "수업", "cooccur_num": 0.9365072250366211}, {"index": 2, "subkeyword": "강의", "cooccur_num": 0.9111408591270447}, {"index": 3, "subkeyword": "영어", "cooccur_num": 0.9099881649017334}, {"index": 4, "subkeyword": "성적", "cooccur_num": 0.8896396160125732}, {"index": 5, "subkeyword": "입시", "cooccur_num": 0.8864453434944153}, {"index": 6, "subkeyword": "진로", "cooccur_num": 0.8852688074111938}, {"index": 7, "subkeyword": "학점", "cooccur_num": 0.8795630931854248}, {"index": 8, "subkeyword": "과목", "cooccur_num": 0.8725976347923279}, {"index": 9, "subkeyword": "진학", "cooccur_num": 0.8639413118362427}, {"index": 10, "subkeyword": "대학생", "cooccur_num": 0.8635173439979553}]}, {"keyword": "오다", "score": 2446, "cooccur": [{"index": 1, "subkeyword": "한국", "cooccur_num": 108}, {"index": 2, "subkeyword": "터", "cooccur_num": 107}, {"index": 3, "subkeyword": "교수", "cooccur_num": 92}, {"index": 4, "subkeyword": "서울", "cooccur_num": 89}, {"index": 5, "subkeyword": "연구", "cooccur_num": 89}, {"index": 6, "subkeyword": "카이스트", "cooccur_num": 89}, {"index": 7, "subkeyword": "늘다", "cooccur_num": 81}, {"index": 8, "subkeyword": "가다", "cooccur_num": 79}, {"index": 9, "subkeyword": "명", "cooccur_num": 73}, {"index": 10, "subkeyword": "기술", "cooccur_num": 73}], "similar": [{"index": 1, "subkeyword": "시작", "cooccur_num": 0.8363139033317566}, {"index": 2, "subkeyword": "월부", "cooccur_num": 0.8266377449035645}, {"index": 3, "subkeyword": "달", "cooccur_num": 0.8190637230873108}, {"index": 4, "subkeyword": "일부", "cooccur_num": 0.8180595636367798}, {"index": 5, "subkeyword": "초", "cooccur_num": 0.8170582056045532}, {"index": 6, "subkeyword": "지난", "cooccur_num": 0.800777792930603}, {"index": 7, "subkeyword": "내년", "cooccur_num": 0.7980876564979553}, {"index": 8, "subkeyword": "예정", "cooccur_num": 0.7706246376037598}, {"index": 9, "subkeyword": "발대식", "cooccur_num": 0.753598690032959}, {"index": 10, "subkeyword": "하반기", "cooccur_num": 0.7532869577407837}]}, {"keyword": "세계", "score": 2332, "cooccur": [{"index": 1, "subkeyword": "대학", "cooccur_num": 241}, {"index": 2, "subkeyword": "최초", "cooccur_num": 189}, {"index": 3, "subkeyword": "연구", "cooccur_num": 181}, {"index": 4, "subkeyword": "수준", "cooccur_num": 170}, {"index": 5, "subkeyword": "최고", "cooccur_num": 168}, {"index": 6, "subkeyword": "분야", "cooccur_num": 133}, {"index": 7, "subkeyword": "개발", "cooccur_num": 131}, {"index": 8, "subkeyword": "한국", "cooccur_num": 122}, {"index": 9, "subkeyword": "기술", "cooccur_num": 118}, {"index": 10, "subkeyword": "교수", "cooccur_num": 115}], "similar": [{"index": 1, "subkeyword": "국내", "cooccur_num": 0.8693867921829224}, {"index": 2, "subkeyword": "우리나라", "cooccur_num": 0.8553179502487183}, {"index": 3, "subkeyword": "자오퉁", "cooccur_num": 0.8415392637252808}, {"index": 4, "subkeyword": "최고", "cooccur_num": 0.8355017900466919}, {"index": 5, "subkeyword": "권위", "cooccur_num": 0.8350297212600708}, {"index": 6, "subkeyword": "최초", "cooccur_num": 0.8308435678482056}, {"index": 7, "subkeyword": "일본", "cooccur_num": 0.8291895389556885}, {"index": 8, "subkeyword": "각국", "cooccur_num": 0.796635627746582}, {"index": 9, "subkeyword": "암호학", "cooccur_num": 0.7947782874107361}, {"index": 10, "subkeyword": "간발", "cooccur_num": 0.7947234511375427}]}, {"keyword": "분야", "score": 2240, "cooccur": [{"index": 1, "subkeyword": "연구", "cooccur_num": 351}, {"index": 2, "subkeyword": "국제", "cooccur_num": 159}, {"index": 3, "subkeyword": "교수", "cooccur_num": 152}, {"index": 4, "subkeyword": "기술", "cooccur_num": 152}, {"index": 5, "subkeyword": "학술지", "cooccur_num": 141}, {"index": 6, "subkeyword": "세계", "cooccur_num": 134}, {"index": 7, "subkeyword": "전문가", "cooccur_num": 110}, {"index": 8, "subkeyword": "과학", "cooccur_num": 99}, {"index": 9, "subkeyword": "결과", "cooccur_num": 98}, {"index": 10, "subkeyword": "산업", "cooccur_num": 98}], "similar": [{"index": 1, "subkeyword": "공로", "cooccur_num": 0.8793737888336182}, {"index": 2, "subkeyword": "기초과학", "cooccur_num": 0.8637139201164246}, {"index": 3, "subkeyword": "해양학", "cooccur_num": 0.8510208129882812}, {"index": 4, "subkeyword": "기초", "cooccur_num": 0.8472908735275269}, {"index": 5, "subkeyword": "학술지", "cooccur_num": 0.8443418741226196}, {"index": 6, "subkeyword": "업적", "cooccur_num": 0.8421759009361267}, {"index": 7, "subkeyword": "생명공학", "cooccur_num": 0.8409779071807861}, {"index": 8, "subkeyword": "결정구조", "cooccur_num": 0.840294599533081}, {"index": 9, "subkeyword": "권위", "cooccur_num": 0.8373630046844482}, {"index": 10, "subkeyword": "생물", "cooccur_num": 0.834771990776062}]}, {"keyword": "과학", "score": 2200, "cooccur": [{"index": 1, "subkeyword": "한국", "cooccur_num": 249}, {"index": 2, "subkeyword": "영재", "cooccur_num": 165}, {"index": 3, "subkeyword": "연구", "cooccur_num": 156}, {"index": 4, "subkeyword": "서울", "cooccur_num": 141}, {"index": 5, "subkeyword": "원", "cooccur_num": 140}, {"index": 6, "subkeyword": "교육", "cooccur_num": 127}, {"index": 7, "subkeyword": "세계", "cooccur_num": 112}, {"index": 8, "subkeyword": "신문", "cooccur_num": 107}, {"index": 9, "subkeyword": "교수", "cooccur_num": 104}, {"index": 10, "subkeyword": "상", "cooccur_num": 100}], "similar": [{"index": 1, "subkeyword": "예술", "cooccur_num": 0.8618221282958984}, {"index": 2, "subkeyword": "영재교육", "cooccur_num": 0.8457041382789612}, {"index": 3, "subkeyword": "올림피아드", "cooccur_num": 0.8400909304618835}, {"index": 4, "subkeyword": "대회", "cooccur_num": 0.8001687526702881}, {"index": 5, "subkeyword": "페임", "cooccur_num": 0.7910667657852173}, {"index": 6, "subkeyword": "영재", "cooccur_num": 0.7901086807250977}, {"index": 7, "subkeyword": "행정가", "cooccur_num": 0.788794994354248}, {"index": 8, "subkeyword": "저술가", "cooccur_num": 0.7859255075454712}, {"index": 9, "subkeyword": "교육평가", "cooccur_num": 0.7717088460922241}, {"index": 10, "subkeyword": "주제", "cooccur_num": 0.7632690668106079}]}, {"keyword": "가다", "score": 2113, "cooccur": [{"index": 1, "subkeyword": "대학", "cooccur_num": 103}, {"index": 2, "subkeyword": "세계", "cooccur_num": 84}, {"index": 3, "subkeyword": "오다", "cooccur_num": 83}, {"index": 4, "subkeyword": "한국", "cooccur_num": 78}, {"index": 5, "subkeyword": "교수", "cooccur_num": 73}, {"index": 6, "subkeyword": "연구", "cooccur_num": 70}, {"index": 7, "subkeyword": "늘다", "cooccur_num": 70}, {"index": 8, "subkeyword": "카이스트", "cooccur_num": 60}, {"index": 9, "subkeyword": "학생", "cooccur_num": 59}, {"index": 10, "subkeyword": "국내", "cooccur_num": 56}], "similar": [{"index": 1, "subkeyword": "처음", "cooccur_num": 0.8824673891067505}, {"index": 2, "subkeyword": "년대", "cooccur_num": 0.8736653923988342}, {"index": 3, "subkeyword": "혼다", "cooccur_num": 0.8542093634605408}, {"index": 4, "subkeyword": "월스트리트저널", "cooccur_num": 0.8528881072998047}, {"index": 5, "subkeyword": "가율", "cooccur_num": 0.8416455984115601}, {"index": 6, "subkeyword": "올리다", "cooccur_num": 0.8413784503936768}, {"index": 7, "subkeyword": "사이버공간", "cooccur_num": 0.829093337059021}, {"index": 8, "subkeyword": "각국", "cooccur_num": 0.8226364254951477}, {"index": 9, "subkeyword": "이름", "cooccur_num": 0.8194559216499329}, {"index": 10, "subkeyword": "마퀴스", "cooccur_num": 0.8188235759735107}]}, {"keyword": "사업", "score": 2083, "cooccur": [{"index": 1, "subkeyword": "지원", "cooccur_num": 181}, {"index": 2, "subkeyword": "추진", "cooccur_num": 143}, {"index": 3, "subkeyword": "단", "cooccur_num": 138}, {"index": 4, "subkeyword": "씨", "cooccur_num": 134}, {"index": 5, "subkeyword": "개발", "cooccur_num": 131}, {"index": 6, "subkeyword": "기술", "cooccur_num": 125}, {"index": 7, "subkeyword": "연구", "cooccur_num": 110}, {"index": 8, "subkeyword": "장", "cooccur_num": 87}, {"index": 9, "subkeyword": "대학", "cooccur_num": 74}, {"index": 10, "subkeyword": "삼성", "cooccur_num": 74}], "similar": [{"index": 1, "subkeyword": "쪽방", "cooccur_num": 0.8979666233062744}, {"index": 2, "subkeyword": "마케팅", "cooccur_num": 0.8578935861587524}, {"index": 3, "subkeyword": "업무", "cooccur_num": 0.8465296626091003}, {"index": 4, "subkeyword": "장축", "cooccur_num": 0.822749137878418}, {"index": 5, "subkeyword": "건설", "cooccur_num": 0.8009481430053711}, {"index": 6, "subkeyword": "전략", "cooccur_num": 0.7974964380264282}, {"index": 7, "subkeyword": "전담", "cooccur_num": 0.7960519194602966}, {"index": 8, "subkeyword": "인텍", "cooccur_num": 0.7951806783676147}, {"index": 9, "subkeyword": "관리", "cooccur_num": 0.7946925163269043}, {"index": 10, "subkeyword": "단", "cooccur_num": 0.7935332655906677}]}, {"keyword": "지원", "score": 2025, "cooccur": [{"index": 1, "subkeyword": "사업", "cooccur_num": 177}, {"index": 2, "subkeyword": "대학", "cooccur_num": 172}, {"index": 3, "subkeyword": "연구", "cooccur_num": 132}, {"index": 4, "subkeyword": "정부", "cooccur_num": 128}, {"index": 5, "subkeyword": "창업", "cooccur_num": 119}, {"index": 6, "subkeyword": "기술", "cooccur_num": 102}, {"index": 7, "subkeyword": "명", "cooccur_num": 95}, {"index": 8, "subkeyword": "기업", "cooccur_num": 89}, {"index": 9, "subkeyword": "센터", "cooccur_num": 80}, {"index": 10, "subkeyword": "도록", "cooccur_num": 71}], "similar": [{"index": 1, "subkeyword": "운영", "cooccur_num": 0.8934217095375061}, {"index": 2, "subkeyword": "예산", "cooccur_num": 0.8920700550079346}, {"index": 3, "subkeyword": "확대", "cooccur_num": 0.8894338011741638}, {"index": 4, "subkeyword": "시행", "cooccur_num": 0.874920666217804}, {"index": 5, "subkeyword": "구비", "cooccur_num": 0.8701183795928955}, {"index": 6, "subkeyword": "인건비", "cooccur_num": 0.8608054518699646}, {"index": 7, "subkeyword": "참여", "cooccur_num": 0.8449392318725586}, {"index": 8, "subkeyword": "수도권", "cooccur_num": 0.8434691429138184}, {"index": 9, "subkeyword": "쪽방", "cooccur_num": 0.8416438698768616}, {"index": 10, "subkeyword": "금", "cooccur_num": 0.8330044746398926}]}, {"keyword": "교육", "score": 1958, "cooccur": [{"index": 1, "subkeyword": "연구", "cooccur_num": 141}, {"index": 2, "subkeyword": "대학", "cooccur_num": 130}, {"index": 3, "subkeyword": "과학", "cooccur_num": 125}, {"index": 4, "subkeyword": "학생", "cooccur_num": 94}, {"index": 5, "subkeyword": "프로그램", "cooccur_num": 89}, {"index": 6, "subkeyword": "기관", "cooccur_num": 81}, {"index": 7, "subkeyword": "원", "cooccur_num": 79}, {"index": 8, "subkeyword": "분야", "cooccur_num": 64}, {"index": 9, "subkeyword": "교수", "cooccur_num": 61}, {"index": 10, "subkeyword": "한국", "cooccur_num": 59}], "similar": [{"index": 1, "subkeyword": "영재", "cooccur_num": 0.8673644065856934}, {"index": 2, "subkeyword": "영재교육", "cooccur_num": 0.8511362075805664}, {"index": 3, "subkeyword": "프로그램", "cooccur_num": 0.8450952768325806}, {"index": 4, "subkeyword": "인재", "cooccur_num": 0.8302502036094666}, {"index": 5, "subkeyword": "청소년", "cooccur_num": 0.812498927116394}, {"index": 6, "subkeyword": "학교", "cooccur_num": 0.8045690655708313}, {"index": 7, "subkeyword": "예술", "cooccur_num": 0.8016482591629028}, {"index": 8, "subkeyword": "창의", "cooccur_num": 0.7964632511138916}, {"index": 9, "subkeyword": "하브", "cooccur_num": 0.7959367036819458}, {"index": 10, "subkeyword": "양성", "cooccur_num": 0.7951322793960571}]}, {"keyword": "미국", "score": 1957, "cooccur": [{"index": 1, "subkeyword": "교수", "cooccur_num": 202}, {"index": 2, "subkeyword": "대학", "cooccur_num": 132}, {"index": 3, "subkeyword": "일본", "cooccur_num": 112}, {"index": 4, "subkeyword": "한국", "cooccur_num": 82}, {"index": 5, "subkeyword": "연구", "cooccur_num": 78}, {"index": 6, "subkeyword": "박사", "cooccur_num": 76}, {"index": 7, "subkeyword": "세계", "cooccur_num": 75}, {"index": 8, "subkeyword": "명", "cooccur_num": 73}, {"index": 9, "subkeyword": "기술", "cooccur_num": 71}, {"index": 10, "subkeyword": "씨", "cooccur_num": 67}], "similar": [{"index": 1, "subkeyword": "영국", "cooccur_num": 0.8835567235946655}, {"index": 2, "subkeyword": "오리건", "cooccur_num": 0.8557004928588867}, {"index": 3, "subkeyword": "독일", "cooccur_num": 0.850578784942627}, {"index": 4, "subkeyword": "도호쿠대", "cooccur_num": 0.8397732973098755}, {"index": 5, "subkeyword": "펜실베니아대", "cooccur_num": 0.8278000354766846}, {"index": 6, "subkeyword": "크립스", "cooccur_num": 0.8229981064796448}, {"index": 7, "subkeyword": "밉다", "cooccur_num": 0.8048058748245239}, {"index": 8, "subkeyword": "정상욱", "cooccur_num": 0.8034504652023315}, {"index": 9, "subkeyword": "박사학위", "cooccur_num": 0.8007398843765259}, {"index": 10, "subkeyword": "중국", "cooccur_num": 0.7973945736885071}]}, {"keyword": "정부", "score": 1929, "cooccur": [{"index": 1, "subkeyword": "출연", "cooccur_num": 207}, {"index": 2, "subkeyword": "지원", "cooccur_num": 124}, {"index": 3, "subkeyword": "연구소", "cooccur_num": 123}, {"index": 4, "subkeyword": "대학", "cooccur_num": 97}, {"index": 5, "subkeyword": "정책", "cooccur_num": 94}, {"index": 6, "subkeyword": "연구", "cooccur_num": 93}, {"index": 7, "subkeyword": "기업", "cooccur_num": 86}, {"index": 8, "subkeyword": "연구기관", "cooccur_num": 80}, {"index": 9, "subkeyword": "민간", "cooccur_num": 75}, {"index": 10, "subkeyword": "청사", "cooccur_num": 73}], "similar": [{"index": 1, "subkeyword": "부처", "cooccur_num": 0.9001170992851257}, {"index": 2, "subkeyword": "출연", "cooccur_num": 0.893733024597168}, {"index": 3, "subkeyword": "대책", "cooccur_num": 0.847514271736145}, {"index": 4, "subkeyword": "세종시", "cooccur_num": 0.8444491028785706}, {"index": 5, "subkeyword": "국가", "cooccur_num": 0.8285945653915405}, {"index": 6, "subkeyword": "방침", "cooccur_num": 0.8229128122329712}, {"index": 7, "subkeyword": "개편", "cooccur_num": 0.8206288814544678}, {"index": 8, "subkeyword": "공약", "cooccur_num": 0.8068710565567017}, {"index": 9, "subkeyword": "방안", "cooccur_num": 0.7996014356613159}, {"index": 10, "subkeyword": "재정", "cooccur_num": 0.7929746508598328}]}, {"keyword": "국내", "score": 1910, "cooccur": [{"index": 1, "subkeyword": "대학", "cooccur_num": 222}, {"index": 2, "subkeyword": "연구진", "cooccur_num": 200}, {"index": 3, "subkeyword": "기술", "cooccur_num": 139}, {"index": 4, "subkeyword": "최초", "cooccur_num": 133}, {"index": 5, "subkeyword": "개발", "cooccur_num": 127}, {"index": 6, "subkeyword": "연구", "cooccur_num": 125}, {"index": 7, "subkeyword": "교수", "cooccur_num": 100}, {"index": 8, "subkeyword": "세계", "cooccur_num": 94}, {"index": 9, "subkeyword": "최고", "cooccur_num": 86}, {"index": 10, "subkeyword": "기업", "cooccur_num": 85}], "similar": [{"index": 1, "subkeyword": "세계", "cooccur_num": 0.8693867921829224}, {"index": 2, "subkeyword": "일본", "cooccur_num": 0.82579106092453}, {"index": 3, "subkeyword": "해외", "cooccur_num": 0.823472261428833}, {"index": 4, "subkeyword": "여타", "cooccur_num": 0.8211514949798584}, {"index": 5, "subkeyword": "특허", "cooccur_num": 0.819528341293335}, {"index": 6, "subkeyword": "출원", "cooccur_num": 0.8136705160140991}, {"index": 7, "subkeyword": "중국", "cooccur_num": 0.7911717891693115}, {"index": 8, "subkeyword": "최초", "cooccur_num": 0.7907977104187012}, {"index": 9, "subkeyword": "산", "cooccur_num": 0.7881187200546265}, {"index": 10, "subkeyword": "유럽", "cooccur_num": 0.782774806022644}]}, {"keyword": "기업", "score": 1887, "cooccur": [{"index": 1, "subkeyword": "들이다", "cooccur_num": 146}, {"index": 2, "subkeyword": "대학", "cooccur_num": 110}, {"index": 3, "subkeyword": "기술", "cooccur_num": 101}, {"index": 4, "subkeyword": "사회적", "cooccur_num": 99}, {"index": 5, "subkeyword": "정부", "cooccur_num": 96}, {"index": 6, "subkeyword": "국내", "cooccur_num": 90}, {"index": 7, "subkeyword": "지원", "cooccur_num": 82}, {"index": 8, "subkeyword": "글로벌", "cooccur_num": 81}, {"index": 9, "subkeyword": "한국", "cooccur_num": 74}, {"index": 10, "subkeyword": "연구소", "cooccur_num": 74}], "similar": [{"index": 1, "subkeyword": "대기업", "cooccur_num": 0.9562625885009766}, {"index": 2, "subkeyword": "벤처기업", "cooccur_num": 0.9027901887893677}, {"index": 3, "subkeyword": "투자", "cooccur_num": 0.8930131793022156}, {"index": 4, "subkeyword": "중소기업", "cooccur_num": 0.8834958672523499}, {"index": 5, "subkeyword": "진출", "cooccur_num": 0.8763639330863953}, {"index": 6, "subkeyword": "스타트업", "cooccur_num": 0.8717705011367798}, {"index": 7, "subkeyword": "주해", "cooccur_num": 0.8389654159545898}, {"index": 8, "subkeyword": "민간", "cooccur_num": 0.8287045359611511}, {"index": 9, "subkeyword": "글로벌", "cooccur_num": 0.8246426582336426}, {"index": 10, "subkeyword": "업계", "cooccur_num": 0.8183823823928833}]}, {"keyword": "밝히다", "score": 1824, "cooccur": [{"index": 1, "subkeyword": "연구", "cooccur_num": 211}, {"index": 2, "subkeyword": "개발", "cooccur_num": 194}, {"index": 3, "subkeyword": "결과", "cooccur_num": 117}, {"index": 4, "subkeyword": "교수", "cooccur_num": 115}, {"index": 5, "subkeyword": "기술", "cooccur_num": 87}, {"index": 6, "subkeyword": "선정", "cooccur_num": 86}, {"index": 7, "subkeyword": "계획", "cooccur_num": 80}, {"index": 8, "subkeyword": "늘다", "cooccur_num": 65}, {"index": 9, "subkeyword": "총장", "cooccur_num": 64}, {"index": 10, "subkeyword": "대학", "cooccur_num": 58}], "similar": [{"index": 1, "subkeyword": "발표", "cooccur_num": 0.7832897901535034}, {"index": 2, "subkeyword": "한편", "cooccur_num": 0.7635241150856018}, {"index": 3, "subkeyword": "공리", "cooccur_num": 0.7503480911254883}, {"index": 4, "subkeyword": "서거", "cooccur_num": 0.746809720993042}, {"index": 5, "subkeyword": "보이콧", "cooccur_num": 0.7366284728050232}, {"index": 6, "subkeyword": "진실성", "cooccur_num": 0.7278201580047607}, {"index": 7, "subkeyword": "셤", "cooccur_num": 0.7192833423614502}, {"index": 8, "subkeyword": "포부", "cooccur_num": 0.7168493270874023}, {"index": 9, "subkeyword": "재계약", "cooccur_num": 0.7162006497383118}, {"index": 10, "subkeyword": "반딧불", "cooccur_num": 0.7075875401496887}]}, {"keyword": "총장", "score": 1790, "cooccur": [{"index": 1, "subkeyword": "서다", "cooccur_num": 380}, {"index": 2, "subkeyword": "서남표", "cooccur_num": 243}, {"index": 3, "subkeyword": "카이스트", "cooccur_num": 238}, {"index": 4, "subkeyword": "대학", "cooccur_num": 148}, {"index": 5, "subkeyword": "린", "cooccur_num": 142}, {"index": 6, "subkeyword": "교수", "cooccur_num": 138}, {"index": 7, "subkeyword": "서울", "cooccur_num": 104}, {"index": 8, "subkeyword": "한국과학기술원", "cooccur_num": 103}, {"index": 9, "subkeyword": "이사회", "cooccur_num": 89}, {"index": 10, "subkeyword": "강성모", "cooccur_num": 86}], "similar": [{"index": 1, "subkeyword": "서남표", "cooccur_num": 0.9290095567703247}, {"index": 2, "subkeyword": "재희", "cooccur_num": 0.9209747314453125}, {"index": 3, "subkeyword": "서다", "cooccur_num": 0.9032767415046692}, {"index": 4, "subkeyword": "러플린", "cooccur_num": 0.9003418684005737}, {"index": 5, "subkeyword": "린", "cooccur_num": 0.8965464234352112}, {"index": 6, "subkeyword": "김한중", "cooccur_num": 0.8845313787460327}, {"index": 7, "subkeyword": "신성철", "cooccur_num": 0.8829131722450256}, {"index": 8, "subkeyword": "백성기", "cooccur_num": 0.8782828450202942}, {"index": 9, "subkeyword": "장제", "cooccur_num": 0.8574859499931335}, {"index": 10, "subkeyword": "강성모", "cooccur_num": 0.8542398810386658}]}, {"keyword": "만들다", "score": 1755, "cooccur": [{"index": 1, "subkeyword": "기술", "cooccur_num": 94}, {"index": 2, "subkeyword": "연구", "cooccur_num": 92}, {"index": 3, "subkeyword": "들이다", "cooccur_num": 80}, {"index": 4, "subkeyword": "세계", "cooccur_num": 58}, {"index": 5, "subkeyword": "대학", "cooccur_num": 57}, {"index": 6, "subkeyword": "사람", "cooccur_num": 53}, {"index": 7, "subkeyword": "로봇", "cooccur_num": 50}, {"index": 8, "subkeyword": "개발", "cooccur_num": 50}, {"index": 9, "subkeyword": "기업", "cooccur_num": 48}, {"index": 10, "subkeyword": "도록", "cooccur_num": 48}], "similar": [{"index": 1, "subkeyword": "인식", "cooccur_num": 0.9123079776763916}, {"index": 2, "subkeyword": "유년기", "cooccur_num": 0.9005424380302429}, {"index": 3, "subkeyword": "인간", "cooccur_num": 0.9005230069160461}, {"index": 4, "subkeyword": "온디맨드", "cooccur_num": 0.8898168802261353}, {"index": 5, "subkeyword": "약육강식", "cooccur_num": 0.8879815340042114}, {"index": 6, "subkeyword": "이미지", "cooccur_num": 0.8866965770721436}, {"index": 7, "subkeyword": "속", "cooccur_num": 0.8856914639472961}, {"index": 8, "subkeyword": "연결", "cooccur_num": 0.8790827989578247}, {"index": 9, "subkeyword": "본성", "cooccur_num": 0.8789666295051575}, {"index": 10, "subkeyword": "밀도", "cooccur_num": 0.876673698425293}]}, {"keyword": "서울대", "score": 1722, "cooccur": [{"index": 1, "subkeyword": "교수", "cooccur_num": 494}, {"index": 2, "subkeyword": "카이스트", "cooccur_num": 170}, {"index": 3, "subkeyword": "대학", "cooccur_num": 145}, {"index": 4, "subkeyword": "명", "cooccur_num": 145}, {"index": 5, "subkeyword": "졸업", "cooccur_num": 120}, {"index": 6, "subkeyword": "병원", "cooccur_num": 111}, {"index": 7, "subkeyword": "씨", "cooccur_num": 106}, {"index": 8, "subkeyword": "서울", "cooccur_num": 90}, {"index": 9, "subkeyword": "연세대", "cooccur_num": 87}, {"index": 10, "subkeyword": "부", "cooccur_num": 85}], "similar": [{"index": 1, "subkeyword": "포", "cooccur_num": 0.9615724682807922}, {"index": 2, "subkeyword": "항공대", "cooccur_num": 0.9499073028564453}, {"index": 3, "subkeyword": "공대", "cooccur_num": 0.9475830793380737}, {"index": 4, "subkeyword": "고려대", "cooccur_num": 0.9458283185958862}, {"index": 5, "subkeyword": "연세대", "cooccur_num": 0.9406208992004395}, {"index": 6, "subkeyword": "국어교육", "cooccur_num": 0.9366531372070312}, {"index": 7, "subkeyword": "의대", "cooccur_num": 0.930367648601532}, {"index": 8, "subkeyword": "임용", "cooccur_num": 0.9286442995071411}, {"index": 9, "subkeyword": "덕환", "cooccur_num": 0.9247060418128967}, {"index": 10, "subkeyword": "성균관대", "cooccur_num": 0.9179092645645142}]}, {"keyword": "산업", "score": 1693, "cooccur": [{"index": 1, "subkeyword": "기술", "cooccur_num": 192}, {"index": 2, "subkeyword": "미래", "cooccur_num": 110}, {"index": 3, "subkeyword": "한국", "cooccur_num": 100}, {"index": 4, "subkeyword": "분야", "cooccur_num": 91}, {"index": 5, "subkeyword": "첨단", "cooccur_num": 90}, {"index": 6, "subkeyword": "차", "cooccur_num": 87}, {"index": 7, "subkeyword": "교수", "cooccur_num": 83}, {"index": 8, "subkeyword": "문화", "cooccur_num": 77}, {"index": 9, "subkeyword": "공학", "cooccur_num": 77}, {"index": 10, "subkeyword": "연구", "cooccur_num": 71}], "similar": [{"index": 1, "subkeyword": "정보통", "cooccur_num": 0.9116480350494385}, {"index": 2, "subkeyword": "신기", "cooccur_num": 0.8867090940475464}, {"index": 3, "subkeyword": "자원부", "cooccur_num": 0.878682017326355}, {"index": 4, "subkeyword": "정보기술", "cooccur_num": 0.8674175143241882}, {"index": 5, "subkeyword": "융합", "cooccur_num": 0.8523956537246704}, {"index": 6, "subkeyword": "디자인", "cooccur_num": 0.8519010543823242}, {"index": 7, "subkeyword": "갈사", "cooccur_num": 0.8511185646057129}, {"index": 8, "subkeyword": "첨단", "cooccur_num": 0.848480224609375}, {"index": 9, "subkeyword": "김정화", "cooccur_num": 0.847976803779602}, {"index": 10, "subkeyword": "이끌다", "cooccur_num": 0.8400192260742188}]}, {"keyword": "과학기술", "score": 1676, "cooccur": [{"index": 1, "subkeyword": "한국", "cooccur_num": 319}, {"index": 2, "subkeyword": "연구원", "cooccur_num": 215}, {"index": 3, "subkeyword": "연구", "cooccur_num": 126}, {"index": 4, "subkeyword": "정책", "cooccur_num": 124}, {"index": 5, "subkeyword": "국가", "cooccur_num": 123}, {"index": 6, "subkeyword": "정보통신부", "cooccur_num": 106}, {"index": 7, "subkeyword": "위성", "cooccur_num": 94}, {"index": 8, "subkeyword": "분야", "cooccur_num": 92}, {"index": 9, "subkeyword": "계", "cooccur_num": 90}, {"index": 10, "subkeyword": "혁신", "cooccur_num": 78}], "similar": [{"index": 1, "subkeyword": "전문사관", "cooccur_num": 0.8829145431518555}, {"index": 2, "subkeyword": "서정욱", "cooccur_num": 0.8787030577659607}, {"index": 3, "subkeyword": "국가", "cooccur_num": 0.862474262714386}, {"index": 4, "subkeyword": "계", "cooccur_num": 0.8597546815872192}, {"index": 5, "subkeyword": "정보통신부", "cooccur_num": 0.8585057258605957}, {"index": 6, "subkeyword": "심의회", "cooccur_num": 0.8451294898986816}, {"index": 7, "subkeyword": "원자력", "cooccur_num": 0.8402878046035767}, {"index": 8, "subkeyword": "과기부", "cooccur_num": 0.8401012420654297}, {"index": 9, "subkeyword": "즈버리", "cooccur_num": 0.8329503536224365}, {"index": 10, "subkeyword": "회의", "cooccur_num": 0.8326078057289124}]}, {"keyword": "연구원", "score": 1624, "cooccur": [{"index": 1, "subkeyword": "한국", "cooccur_num": 699}, {"index": 2, "subkeyword": "과학기술", "cooccur_num": 212}, {"index": 3, "subkeyword": "연구", "cooccur_num": 190}, {"index": 4, "subkeyword": "기술", "cooccur_num": 136}, {"index": 5, "subkeyword": "장", "cooccur_num": 136}, {"index": 6, "subkeyword": "연구소", "cooccur_num": 134}, {"index": 7, "subkeyword": "기초과학", "cooccur_num": 121}, {"index": 8, "subkeyword": "원장", "cooccur_num": 111}, {"index": 9, "subkeyword": "교수", "cooccur_num": 105}, {"index": 10, "subkeyword": "과학", "cooccur_num": 93}], "similar": [{"index": 1, "subkeyword": "항공우주", "cooccur_num": 0.891892671585083}, {"index": 2, "subkeyword": "원자력", "cooccur_num": 0.869340717792511}, {"index": 3, "subkeyword": "연구소", "cooccur_num": 0.8498294353485107}, {"index": 4, "subkeyword": "전자통신", "cooccur_num": 0.844421923160553}, {"index": 5, "subkeyword": "오세정", "cooccur_num": 0.8345794081687927}, {"index": 6, "subkeyword": "신정", "cooccur_num": 0.8235530853271484}, {"index": 7, "subkeyword": "박용곤", "cooccur_num": 0.8166059851646423}, {"index": 8, "subkeyword": "김은영", "cooccur_num": 0.813899040222168}, {"index": 9, "subkeyword": "성연", "cooccur_num": 0.8084295988082886}, {"index": 10, "subkeyword": "리켄", "cooccur_num": 0.8030780553817749}]}, {"keyword": "문제", "score": 1613, "cooccur": [{"index": 1, "subkeyword": "해결", "cooccur_num": 217}, {"index": 2, "subkeyword": "사회", "cooccur_num": 69}, {"index": 3, "subkeyword": "늘다", "cooccur_num": 61}, {"index": 4, "subkeyword": "연구", "cooccur_num": 60}, {"index": 5, "subkeyword": "해", "cooccur_num": 57}, {"index": 6, "subkeyword": "들이다", "cooccur_num": 56}, {"index": 7, "subkeyword": "교수", "cooccur_num": 54}, {"index": 8, "subkeyword": "학생", "cooccur_num": 54}, {"index": 9, "subkeyword": "총장", "cooccur_num": 51}, {"index": 10, "subkeyword": "결하", "cooccur_num": 51}], "similar": [{"index": 1, "subkeyword": "지적", "cooccur_num": 0.9600464701652527}, {"index": 2, "subkeyword": "해결", "cooccur_num": 0.9368150234222412}, {"index": 3, "subkeyword": "제풀이", "cooccur_num": 0.9058414697647095}, {"index": 4, "subkeyword": "제대로", "cooccur_num": 0.902193009853363}, {"index": 5, "subkeyword": "필", "cooccur_num": 0.8988503217697144}, {"index": 6, "subkeyword": "요하", "cooccur_num": 0.8891981244087219}, {"index": 7, "subkeyword": "게", "cooccur_num": 0.8859596848487854}, {"index": 8, "subkeyword": "정적", "cooccur_num": 0.8855522871017456}, {"index": 9, "subkeyword": "입장", "cooccur_num": 0.882946252822876}, {"index": 10, "subkeyword": "주장", "cooccur_num": 0.8821281790733337}]}, {"keyword": "지난", "score": 1538, "cooccur": [{"index": 1, "subkeyword": "교수", "cooccur_num": 92}, {"index": 2, "subkeyword": "서울", "cooccur_num": 86}, {"index": 3, "subkeyword": "터", "cooccur_num": 82}, {"index": 4, "subkeyword": "연구", "cooccur_num": 68}, {"index": 5, "subkeyword": "카이스트", "cooccur_num": 64}, {"index": 6, "subkeyword": "한국", "cooccur_num": 61}, {"index": 7, "subkeyword": "명", "cooccur_num": 53}, {"index": 8, "subkeyword": "늘다", "cooccur_num": 53}, {"index": 9, "subkeyword": "미국", "cooccur_num": 52}, {"index": 10, "subkeyword": "밝히다", "cooccur_num": 49}], "similar": [{"index": 1, "subkeyword": "지난달", "cooccur_num": 0.8480908870697021}, {"index": 2, "subkeyword": "월부", "cooccur_num": 0.8056435585021973}, {"index": 3, "subkeyword": "첫", "cooccur_num": 0.8011243939399719}, {"index": 4, "subkeyword": "오다", "cooccur_num": 0.800777792930603}, {"index": 5, "subkeyword": "취임", "cooccur_num": 0.7991350889205933}, {"index": 6, "subkeyword": "이튿날", "cooccur_num": 0.7982196807861328}, {"index": 7, "subkeyword": "방문", "cooccur_num": 0.7929437160491943}, {"index": 8, "subkeyword": "정기", "cooccur_num": 0.7884364128112793}, {"index": 9, "subkeyword": "주년", "cooccur_num": 0.7861584424972534}, {"index": 10, "subkeyword": "열리다", "cooccur_num": 0.7850731015205383}]}, {"keyword": "대표", "score": 1506, "cooccur": [{"index": 1, "subkeyword": "씨", "cooccur_num": 207}, {"index": 2, "subkeyword": "김", "cooccur_num": 114}, {"index": 3, "subkeyword": "공동", "cooccur_num": 86}, {"index": 4, "subkeyword": "안", "cooccur_num": 80}, {"index": 5, "subkeyword": "한국", "cooccur_num": 70}, {"index": 6, "subkeyword": "상", "cooccur_num": 59}, {"index": 7, "subkeyword": "교수", "cooccur_num": 58}, {"index": 8, "subkeyword": "서울", "cooccur_num": 48}, {"index": 9, "subkeyword": "부친상", "cooccur_num": 48}, {"index": 10, "subkeyword": "오전", "cooccur_num": 46}], "similar": [{"index": 1, "subkeyword": "회장", "cooccur_num": 0.9473592638969421}, {"index": 2, "subkeyword": "부회장", "cooccur_num": 0.9022903442382812}, {"index": 3, "subkeyword": "김정주", "cooccur_num": 0.900444507598877}, {"index": 4, "subkeyword": "대표이사", "cooccur_num": 0.8990467190742493}, {"index": 5, "subkeyword": "최태원", "cooccur_num": 0.8973909020423889}, {"index": 6, "subkeyword": "최신원", "cooccur_num": 0.8964583873748779}, {"index": 7, "subkeyword": "엔씨소프트", "cooccur_num": 0.8961108922958374}, {"index": 8, "subkeyword": "장영신", "cooccur_num": 0.8915644288063049}, {"index": 9, "subkeyword": "삼화", "cooccur_num": 0.8914749622344971}, {"index": 10, "subkeyword": "사장", "cooccur_num": 0.8869072794914246}]}, {"keyword": "사람", "score": 1452, "cooccur": [{"index": 1, "subkeyword": "들이다", "cooccur_num": 190}, {"index": 2, "subkeyword": "늘다", "cooccur_num": 62}, {"index": 3, "subkeyword": "교수", "cooccur_num": 56}, {"index": 4, "subkeyword": "연구", "cooccur_num": 52}, {"index": 5, "subkeyword": "만들다", "cooccur_num": 50}, {"index": 6, "subkeyword": "좋다", "cooccur_num": 39}, {"index": 7, "subkeyword": "이나", "cooccur_num": 36}, {"index": 8, "subkeyword": "가장", "cooccur_num": 33}, {"index": 9, "subkeyword": "사랑", "cooccur_num": 31}, {"index": 10, "subkeyword": "명", "cooccur_num": 31}], "similar": [{"index": 1, "subkeyword": "느끼다", "cooccur_num": 0.925143301486969}, {"index": 2, "subkeyword": "자다", "cooccur_num": 0.9012887477874756}, {"index": 3, "subkeyword": "알다", "cooccur_num": 0.8918101787567139}, {"index": 4, "subkeyword": "모르다", "cooccur_num": 0.8828274607658386}, {"index": 5, "subkeyword": "책", "cooccur_num": 0.8805018067359924}, {"index": 6, "subkeyword": "이야기", "cooccur_num": 0.87862229347229}, {"index": 7, "subkeyword": "지언", "cooccur_num": 0.878142774105072}, {"index": 8, "subkeyword": "읽다", "cooccur_num": 0.8751826286315918}, {"index": 9, "subkeyword": "마음", "cooccur_num": 0.866254985332489}, {"index": 10, "subkeyword": "찾다", "cooccur_num": 0.8628969192504883}]}, {"keyword": "학교", "score": 1408, "cooccur": [{"index": 1, "subkeyword": "학생", "cooccur_num": 155}, {"index": 2, "subkeyword": "영재", "cooccur_num": 140}, {"index": 3, "subkeyword": "교수", "cooccur_num": 94}, {"index": 4, "subkeyword": "과학", "cooccur_num": 88}, {"index": 5, "subkeyword": "총장", "cooccur_num": 62}, {"index": 6, "subkeyword": "늘다", "cooccur_num": 57}, {"index": 7, "subkeyword": "한국", "cooccur_num": 57}, {"index": 8, "subkeyword": "대학", "cooccur_num": 56}, {"index": 9, "subkeyword": "들이다", "cooccur_num": 55}, {"index": 10, "subkeyword": "측", "cooccur_num": 54}], "similar": [{"index": 1, "subkeyword": "영재", "cooccur_num": 0.9057488441467285}, {"index": 2, "subkeyword": "캠프", "cooccur_num": 0.9029253721237183}, {"index": 3, "subkeyword": "과학고", "cooccur_num": 0.895466685295105}, {"index": 4, "subkeyword": "다문화", "cooccur_num": 0.8816181421279907}, {"index": 5, "subkeyword": "카이스트신문", "cooccur_num": 0.8772474527359009}, {"index": 6, "subkeyword": "입시", "cooccur_num": 0.872015118598938}, {"index": 7, "subkeyword": "고교", "cooccur_num": 0.8667635917663574}, {"index": 8, "subkeyword": "원어민", "cooccur_num": 0.8636083602905273}, {"index": 9, "subkeyword": "영어", "cooccur_num": 0.8623282313346863}, {"index": 10, "subkeyword": "학부모", "cooccur_num": 0.8552260398864746}]}, {"keyword": "오전", "score": 1377, "cooccur": [{"index": 1, "subkeyword": "발인", "cooccur_num": 1089}, {"index": 2, "subkeyword": "병원", "cooccur_num": 609}, {"index": 3, "subkeyword": "서울", "cooccur_num": 547}, {"index": 4, "subkeyword": "삼성", "cooccur_num": 240}, {"index": 5, "subkeyword": "아산병원", "cooccur_num": 214}, {"index": 6, "subkeyword": "상", "cooccur_num": 212}, {"index": 7, "subkeyword": "씨", "cooccur_num": 101}, {"index": 8, "subkeyword": "장", "cooccur_num": 97}, {"index": 9, "subkeyword": "부친상", "cooccur_num": 94}, {"index": 10, "subkeyword": "장례식", "cooccur_num": 86}], "similar": [{"index": 1, "subkeyword": "발인", "cooccur_num": 0.9598792195320129}, {"index": 2, "subkeyword": "장례식", "cooccur_num": 0.9569937586784363}, {"index": 3, "subkeyword": "병원", "cooccur_num": 0.9395349025726318}, {"index": 4, "subkeyword": "장지", "cooccur_num": 0.9392403960227966}, {"index": 5, "subkeyword": "기독", "cooccur_num": 0.9299823641777039}, {"index": 6, "subkeyword": "태안군", "cooccur_num": 0.9259490966796875}, {"index": 7, "subkeyword": "장례", "cooccur_num": 0.9241596460342407}, {"index": 8, "subkeyword": "성재", "cooccur_num": 0.9237704873085022}, {"index": 9, "subkeyword": "김혜경", "cooccur_num": 0.9197766780853271}, {"index": 10, "subkeyword": "유한킴벌리", "cooccur_num": 0.9186314940452576}]}, {"keyword": "한국과학기술원", "score": 1354, "cooccur": [{"index": 1, "subkeyword": "교수", "cooccur_num": 315}, {"index": 2, "subkeyword": "은", "cooccur_num": 107}, {"index": 3, "subkeyword": "총장", "cooccur_num": 105}, {"index": 4, "subkeyword": "카이스트", "cooccur_num": 101}, {"index": 5, "subkeyword": "연구", "cooccur_num": 88}, {"index": 6, "subkeyword": "개발", "cooccur_num": 86}, {"index": 7, "subkeyword": "서울대", "cooccur_num": 78}, {"index": 8, "subkeyword": "박사", "cooccur_num": 72}, {"index": 9, "subkeyword": "한국", "cooccur_num": 70}, {"index": 10, "subkeyword": "대전", "cooccur_num": 65}], "similar": [{"index": 1, "subkeyword": "석좌교수", "cooccur_num": 0.9198305010795593}, {"index": 2, "subkeyword": "김종환", "cooccur_num": 0.9128624200820923}, {"index": 3, "subkeyword": "윤덕용", "cooccur_num": 0.905880331993103}, {"index": 4, "subkeyword": "우운", "cooccur_num": 0.9009301662445068}, {"index": 5, "subkeyword": "신소재공학", "cooccur_num": 0.8964941501617432}, {"index": 6, "subkeyword": "기계공학", "cooccur_num": 0.8946324586868286}, {"index": 7, "subkeyword": "고다드", "cooccur_num": 0.8923537731170654}, {"index": 8, "subkeyword": "정재승", "cooccur_num": 0.8819093704223633}, {"index": 9, "subkeyword": "이상엽", "cooccur_num": 0.881903886795044}, {"index": 10, "subkeyword": "전자공학", "cooccur_num": 0.8785608410835266}]}, {"keyword": "과정", "score": 1343, "cooccur": [{"index": 1, "subkeyword": "박사", "cooccur_num": 278}, {"index": 2, "subkeyword": "석", "cooccur_num": 73}, {"index": 3, "subkeyword": "학생", "cooccur_num": 73}, {"index": 4, "subkeyword": "대학", "cooccur_num": 64}, {"index": 5, "subkeyword": "교수", "cooccur_num": 56}, {"index": 6, "subkeyword": "거치다", "cooccur_num": 54}, {"index": 7, "subkeyword": "대학원", "cooccur_num": 51}, {"index": 8, "subkeyword": "카이스트", "cooccur_num": 50}, {"index": 9, "subkeyword": "연구", "cooccur_num": 49}, {"index": 10, "subkeyword": "개설", "cooccur_num": 47}], "similar": [{"index": 1, "subkeyword": "슈렉", "cooccur_num": 0.8587932586669922}, {"index": 2, "subkeyword": "맥밀런", "cooccur_num": 0.8395581245422363}, {"index": 3, "subkeyword": "전문요원", "cooccur_num": 0.7898225784301758}, {"index": 4, "subkeyword": "학사", "cooccur_num": 0.7822550535202026}, {"index": 5, "subkeyword": "개설", "cooccur_num": 0.7603642344474792}, {"index": 6, "subkeyword": "교과목", "cooccur_num": 0.7580380439758301}, {"index": 7, "subkeyword": "교과", "cooccur_num": 0.7355449795722961}, {"index": 8, "subkeyword": "전공", "cooccur_num": 0.7280060052871704}, {"index": 9, "subkeyword": "범재", "cooccur_num": 0.723801851272583}, {"index": 10, "subkeyword": "과목", "cooccur_num": 0.7230398058891296}]}, {"keyword": "센터", "score": 1342, "cooccur": [{"index": 1, "subkeyword": "연구", "cooccur_num": 350}, {"index": 2, "subkeyword": "장", "cooccur_num": 227}, {"index": 3, "subkeyword": "혁신", "cooccur_num": 152}, {"index": 4, "subkeyword": "지원", "cooccur_num": 80}, {"index": 5, "subkeyword": "창조경제", "cooccur_num": 80}, {"index": 6, "subkeyword": "서울", "cooccur_num": 79}, {"index": 7, "subkeyword": "기술", "cooccur_num": 78}, {"index": 8, "subkeyword": "인공위성", "cooccur_num": 69}, {"index": 9, "subkeyword": "대전", "cooccur_num": 68}, {"index": 10, "subkeyword": "소장", "cooccur_num": 66}], "similar": [{"index": 1, "subkeyword": "로케이션", "cooccur_num": 0.8412941098213196}, {"index": 2, "subkeyword": "심은섭", "cooccur_num": 0.8300772905349731}, {"index": 3, "subkeyword": "이재우", "cooccur_num": 0.8281513452529907}, {"index": 4, "subkeyword": "소장", "cooccur_num": 0.8174721002578735}, {"index": 5, "subkeyword": "인공위성", "cooccur_num": 0.813774824142456}, {"index": 6, "subkeyword": "분소", "cooccur_num": 0.7979782819747925}, {"index": 7, "subkeyword": "개소식", "cooccur_num": 0.7973777651786804}, {"index": 8, "subkeyword": "최순달", "cooccur_num": 0.7780358791351318}, {"index": 9, "subkeyword": "미래전략대학원", "cooccur_num": 0.7741032838821411}, {"index": 10, "subkeyword": "단장", "cooccur_num": 0.7723225951194763}]}, {"keyword": "삼성", "score": 1320, "cooccur": [{"index": 1, "subkeyword": "씨", "cooccur_num": 289}, {"index": 2, "subkeyword": "서울", "cooccur_num": 263}, {"index": 3, "subkeyword": "병원", "cooccur_num": 253}, {"index": 4, "subkeyword": "발인", "cooccur_num": 232}, {"index": 5, "subkeyword": "사장", "cooccur_num": 152}, {"index": 6, "subkeyword": "상", "cooccur_num": 114}, {"index": 7, "subkeyword": "생명", "cooccur_num": 85}, {"index": 8, "subkeyword": "기술", "cooccur_num": 77}, {"index": 9, "subkeyword": "사업", "cooccur_num": 70}, {"index": 10, "subkeyword": "회장", "cooccur_num": 69}], "similar": [{"index": 1, "subkeyword": "코닝", "cooccur_num": 0.914750337600708}, {"index": 2, "subkeyword": "한화", "cooccur_num": 0.9115426540374756}, {"index": 3, "subkeyword": "영업", "cooccur_num": 0.9017386436462402}, {"index": 4, "subkeyword": "은행", "cooccur_num": 0.8936737775802612}, {"index": 5, "subkeyword": "증권", "cooccur_num": 0.8826897740364075}, {"index": 6, "subkeyword": "그룹", "cooccur_num": 0.8805393576622009}, {"index": 7, "subkeyword": "솔베이", "cooccur_num": 0.8754572868347168}, {"index": 8, "subkeyword": "텔레콤", "cooccur_num": 0.8692034482955933}, {"index": 9, "subkeyword": "바이오넷", "cooccur_num": 0.8671180605888367}, {"index": 10, "subkeyword": "사장", "cooccur_num": 0.863052248954773}]}, {"keyword": "평가", "score": 1255, "cooccur": [{"index": 1, "subkeyword": "대학", "cooccur_num": 96}, {"index": 2, "subkeyword": "교수", "cooccur_num": 83}, {"index": 3, "subkeyword": "기술", "cooccur_num": 75}, {"index": 4, "subkeyword": "연구", "cooccur_num": 74}, {"index": 5, "subkeyword": "세계", "cooccur_num": 67}, {"index": 6, "subkeyword": "결과", "cooccur_num": 59}, {"index": 7, "subkeyword": "점", "cooccur_num": 49}, {"index": 8, "subkeyword": "늘다", "cooccur_num": 47}, {"index": 9, "subkeyword": "사업", "cooccur_num": 46}, {"index": 10, "subkeyword": "높다", "cooccur_num": 43}], "similar": [{"index": 1, "subkeyword": "실적", "cooccur_num": 0.8868933916091919}, {"index": 2, "subkeyword": "해당", "cooccur_num": 0.8652939796447754}, {"index": 3, "subkeyword": "별", "cooccur_num": 0.8651015758514404}, {"index": 4, "subkeyword": "도입", "cooccur_num": 0.8499161005020142}, {"index": 5, "subkeyword": "인정", "cooccur_num": 0.8441284894943237}, {"index": 6, "subkeyword": "강화", "cooccur_num": 0.8410340547561646}, {"index": 7, "subkeyword": "전문요원", "cooccur_num": 0.8358548879623413}, {"index": 8, "subkeyword": "성과", "cooccur_num": 0.8318347334861755}, {"index": 9, "subkeyword": "우수", "cooccur_num": 0.8305866122245789}, {"index": 10, "subkeyword": "집중", "cooccur_num": 0.8280057311058044}]}, {"keyword": "계획", "score": 1252, "cooccur": [{"index": 1, "subkeyword": "연구", "cooccur_num": 92}, {"index": 2, "subkeyword": "밝히다", "cooccur_num": 79}, {"index": 3, "subkeyword": "개발", "cooccur_num": 77}, {"index": 4, "subkeyword": "사업", "cooccur_num": 64}, {"index": 5, "subkeyword": "발표", "cooccur_num": 62}, {"index": 6, "subkeyword": "정부", "cooccur_num": 56}, {"index": 7, "subkeyword": "지원", "cooccur_num": 54}, {"index": 8, "subkeyword": "추진", "cooccur_num": 53}, {"index": 9, "subkeyword": "수립", "cooccur_num": 51}, {"index": 10, "subkeyword": "기본", "cooccur_num": 44}], "similar": [{"index": 1, "subkeyword": "추진", "cooccur_num": 0.9328259229660034}, {"index": 2, "subkeyword": "방침", "cooccur_num": 0.8757014274597168}, {"index": 3, "subkeyword": "기록물", "cooccur_num": 0.8597882986068726}, {"index": 4, "subkeyword": "수립", "cooccur_num": 0.8590108156204224}, {"index": 5, "subkeyword": "확대", "cooccur_num": 0.8589410781860352}, {"index": 6, "subkeyword": "명선", "cooccur_num": 0.8570082187652588}, {"index": 7, "subkeyword": "이전", "cooccur_num": 0.8432502746582031}, {"index": 8, "subkeyword": "연구개발", "cooccur_num": 0.8411663174629211}, {"index": 9, "subkeyword": "예산", "cooccur_num": 0.8404996395111084}, {"index": 10, "subkeyword": "본격", "cooccur_num": 0.8395091891288757}]}, {"keyword": "연구소", "score": 1235, "cooccur": [{"index": 1, "subkeyword": "연구", "cooccur_num": 140}, {"index": 2, "subkeyword": "연구원", "cooccur_num": 136}, {"index": 3, "subkeyword": "정부", "cooccur_num": 127}, {"index": 4, "subkeyword": "출연", "cooccur_num": 126}, {"index": 5, "subkeyword": "한국", "cooccur_num": 114}, {"index": 6, "subkeyword": "대학", "cooccur_num": 107}, {"index": 7, "subkeyword": "기술", "cooccur_num": 85}, {"index": 8, "subkeyword": "기업", "cooccur_num": 73}, {"index": 9, "subkeyword": "교수", "cooccur_num": 71}, {"index": 10, "subkeyword": "미국", "cooccur_num": 67}], "similar": [{"index": 1, "subkeyword": "생명공학", "cooccur_num": 0.8826004266738892}, {"index": 2, "subkeyword": "김은영", "cooccur_num": 0.8813474178314209}, {"index": 3, "subkeyword": "리버모어", "cooccur_num": 0.8749700784683228}, {"index": 4, "subkeyword": "크립스", "cooccur_num": 0.8714593648910522}, {"index": 5, "subkeyword": "항공우주", "cooccur_num": 0.8680687546730042}, {"index": 6, "subkeyword": "리켄", "cooccur_num": 0.8639016151428223}, {"index": 7, "subkeyword": "원자력", "cooccur_num": 0.8524726033210754}, {"index": 8, "subkeyword": "부설", "cooccur_num": 0.8517807722091675}, {"index": 9, "subkeyword": "연구원", "cooccur_num": 0.8498294353485107}, {"index": 10, "subkeyword": "연구기관", "cooccur_num": 0.8458678722381592}]}, {"keyword": "박사", "score": 1225, "cooccur": [{"index": 1, "subkeyword": "과정", "cooccur_num": 276}, {"index": 2, "subkeyword": "석", "cooccur_num": 175}, {"index": 3, "subkeyword": "학위", "cooccur_num": 169}, {"index": 4, "subkeyword": "교수", "cooccur_num": 105}, {"index": 5, "subkeyword": "명", "cooccur_num": 101}, {"index": 6, "subkeyword": "연구", "cooccur_num": 89}, {"index": 7, "subkeyword": "카이스트", "cooccur_num": 87}, {"index": 8, "subkeyword": "미국", "cooccur_num": 86}, {"index": 9, "subkeyword": "한국과학기술원", "cooccur_num": 81}, {"index": 10, "subkeyword": "팀", "cooccur_num": 65}], "similar": [{"index": 1, "subkeyword": "학위", "cooccur_num": 0.8976686000823975}, {"index": 2, "subkeyword": "석", "cooccur_num": 0.8903276324272156}, {"index": 3, "subkeyword": "고다드", "cooccur_num": 0.88088059425354}, {"index": 4, "subkeyword": "석사", "cooccur_num": 0.8779568672180176}, {"index": 5, "subkeyword": "박사학위", "cooccur_num": 0.8737671971321106}, {"index": 6, "subkeyword": "슈렉", "cooccur_num": 0.873046875}, {"index": 7, "subkeyword": "일리노이주립대", "cooccur_num": 0.8674668073654175}, {"index": 8, "subkeyword": "류근철", "cooccur_num": 0.855108380317688}, {"index": 9, "subkeyword": "기계공학", "cooccur_num": 0.847632884979248}, {"index": 10, "subkeyword": "정상욱", "cooccur_num": 0.8457480669021606}]}, {"keyword": "정책", "score": 1220, "cooccur": [{"index": 1, "subkeyword": "과학기술", "cooccur_num": 113}, {"index": 2, "subkeyword": "관", "cooccur_num": 98}, {"index": 3, "subkeyword": "정부", "cooccur_num": 96}, {"index": 4, "subkeyword": "장", "cooccur_num": 91}, {"index": 5, "subkeyword": "연구", "cooccur_num": 63}, {"index": 6, "subkeyword": "기획", "cooccur_num": 60}, {"index": 7, "subkeyword": "연구원", "cooccur_num": 56}, {"index": 8, "subkeyword": "실장", "cooccur_num": 54}, {"index": 9, "subkeyword": "교육", "cooccur_num": 50}, {"index": 10, "subkeyword": "국장", "cooccur_num": 48}], "similar": [{"index": 1, "subkeyword": "부처", "cooccur_num": 0.9113025069236755}, {"index": 2, "subkeyword": "위원회", "cooccur_num": 0.8674887418746948}, {"index": 3, "subkeyword": "한경제", "cooccur_num": 0.8644824624061584}, {"index": 4, "subkeyword": "대책", "cooccur_num": 0.8617726564407349}, {"index": 5, "subkeyword": "복지", "cooccur_num": 0.8616071939468384}, {"index": 6, "subkeyword": "정과정", "cooccur_num": 0.8471136093139648}, {"index": 7, "subkeyword": "자문", "cooccur_num": 0.8438125848770142}, {"index": 8, "subkeyword": "통합", "cooccur_num": 0.8417620658874512}, {"index": 9, "subkeyword": "개편", "cooccur_num": 0.841420590877533}, {"index": 10, "subkeyword": "과기부", "cooccur_num": 0.8388587832450867}]}, {"keyword": "회장", "score": 1210, "cooccur": [{"index": 1, "subkeyword": "한국", "cooccur_num": 107}, {"index": 2, "subkeyword": "그룹", "cooccur_num": 106}, {"index": 3, "subkeyword": "김", "cooccur_num": 86}, {"index": 4, "subkeyword": "회", "cooccur_num": 80}, {"index": 5, "subkeyword": "씨", "cooccur_num": 74}, {"index": 6, "subkeyword": "삼성", "cooccur_num": 70}, {"index": 7, "subkeyword": "서울", "cooccur_num": 55}, {"index": 8, "subkeyword": "금융", "cooccur_num": 51}, {"index": 9, "subkeyword": "교수", "cooccur_num": 50}, {"index": 10, "subkeyword": "경영", "cooccur_num": 48}], "similar": [{"index": 1, "subkeyword": "장영신", "cooccur_num": 0.9503624439239502}, {"index": 2, "subkeyword": "대표", "cooccur_num": 0.9473592638969421}, {"index": 3, "subkeyword": "최태원", "cooccur_num": 0.9326140880584717}, {"index": 4, "subkeyword": "최신원", "cooccur_num": 0.9181127548217773}, {"index": 5, "subkeyword": "부회장", "cooccur_num": 0.9175386428833008}, {"index": 6, "subkeyword": "구본무", "cooccur_num": 0.9160560965538025}, {"index": 7, "subkeyword": "의장", "cooccur_num": 0.9105589389801025}, {"index": 8, "subkeyword": "정담", "cooccur_num": 0.9053465723991394}, {"index": 9, "subkeyword": "지내다", "cooccur_num": 0.9041768312454224}, {"index": 10, "subkeyword": "김영찬", "cooccur_num": 0.9040334224700928}]}, {"keyword": "사회", "score": 1206, "cooccur": [{"index": 1, "subkeyword": "문제", "cooccur_num": 72}, {"index": 2, "subkeyword": "교수", "cooccur_num": 69}, {"index": 3, "subkeyword": "한국", "cooccur_num": 66}, {"index": 4, "subkeyword": "공헌", "cooccur_num": 65}, {"index": 5, "subkeyword": "인문", "cooccur_num": 62}, {"index": 6, "subkeyword": "대학", "cooccur_num": 60}, {"index": 7, "subkeyword": "분야", "cooccur_num": 49}, {"index": 8, "subkeyword": "경제", "cooccur_num": 45}, {"index": 9, "subkeyword": "늘다", "cooccur_num": 44}, {"index": 10, "subkeyword": "변화", "cooccur_num": 43}], "similar": [{"index": 1, "subkeyword": "강조", "cooccur_num": 0.8786518573760986}, {"index": 2, "subkeyword": "공헌", "cooccur_num": 0.8573381900787354}, {"index": 3, "subkeyword": "소통", "cooccur_num": 0.8483611941337585}, {"index": 4, "subkeyword": "행복감", "cooccur_num": 0.8302929997444153}, {"index": 5, "subkeyword": "국민", "cooccur_num": 0.826129674911499}, {"index": 6, "subkeyword": "복지", "cooccur_num": 0.8243650197982788}, {"index": 7, "subkeyword": "정신", "cooccur_num": 0.8220762610435486}, {"index": 8, "subkeyword": "의적", "cooccur_num": 0.8156523108482361}, {"index": 9, "subkeyword": "다인", "cooccur_num": 0.8110025525093079}, {"index": 10, "subkeyword": "바뀌다", "cooccur_num": 0.8094243407249451}]}, {"keyword": "관련", "score": 1197, "cooccur": [{"index": 1, "subkeyword": "기술", "cooccur_num": 80}, {"index": 2, "subkeyword": "연구", "cooccur_num": 79}, {"index": 3, "subkeyword": "분야", "cooccur_num": 73}, {"index": 4, "subkeyword": "개발", "cooccur_num": 48}, {"index": 5, "subkeyword": "산업", "cooccur_num": 46}, {"index": 6, "subkeyword": "대학", "cooccur_num": 43}, {"index": 7, "subkeyword": "교수", "cooccur_num": 43}, {"index": 8, "subkeyword": "기업", "cooccur_num": 38}, {"index": 9, "subkeyword": "학생", "cooccur_num": 34}, {"index": 10, "subkeyword": "들이다", "cooccur_num": 33}], "similar": [{"index": 1, "subkeyword": "중점", "cooccur_num": 0.9235665202140808}, {"index": 2, "subkeyword": "역량", "cooccur_num": 0.9225566387176514}, {"index": 3, "subkeyword": "기초", "cooccur_num": 0.9224848747253418}, {"index": 4, "subkeyword": "인력", "cooccur_num": 0.9160909652709961}, {"index": 5, "subkeyword": "실무", "cooccur_num": 0.9113469123840332}, {"index": 6, "subkeyword": "집중", "cooccur_num": 0.9093716144561768}, {"index": 7, "subkeyword": "고급", "cooccur_num": 0.9053232669830322}, {"index": 8, "subkeyword": "강화", "cooccur_num": 0.9040290713310242}, {"index": 9, "subkeyword": "구성", "cooccur_num": 0.9020254611968994}, {"index": 10, "subkeyword": "교류", "cooccur_num": 0.8984304666519165}]}, {"keyword": "지난해", "score": 1168, "cooccur": [{"index": 1, "subkeyword": "명", "cooccur_num": 104}, {"index": 2, "subkeyword": "대학", "cooccur_num": 65}, {"index": 3, "subkeyword": "교수", "cooccur_num": 53}, {"index": 4, "subkeyword": "늘다", "cooccur_num": 50}, {"index": 5, "subkeyword": "한국", "cooccur_num": 49}, {"index": 6, "subkeyword": "올해", "cooccur_num": 48}, {"index": 7, "subkeyword": "연구", "cooccur_num": 37}, {"index": 8, "subkeyword": "카이스트", "cooccur_num": 36}, {"index": 9, "subkeyword": "미국", "cooccur_num": 36}, {"index": 10, "subkeyword": "학생", "cooccur_num": 35}], "similar": [{"index": 1, "subkeyword": "올해", "cooccur_num": 0.9117997288703918}, {"index": 2, "subkeyword": "가운데", "cooccur_num": 0.9066001772880554}, {"index": 3, "subkeyword": "총", "cooccur_num": 0.8867827653884888}, {"index": 4, "subkeyword": "순위", "cooccur_num": 0.8721733093261719}, {"index": 5, "subkeyword": "오믹스", "cooccur_num": 0.8650356531143188}, {"index": 6, "subkeyword": "기록", "cooccur_num": 0.8621586561203003}, {"index": 7, "subkeyword": "년도", "cooccur_num": 0.8610261082649231}, {"index": 8, "subkeyword": "차지", "cooccur_num": 0.8598281741142273}, {"index": 9, "subkeyword": "매년", "cooccur_num": 0.8584991693496704}, {"index": 10, "subkeyword": "개교", "cooccur_num": 0.8557217121124268}]}, {"keyword": "국제", "score": 1136, "cooccur": [{"index": 1, "subkeyword": "학술지", "cooccur_num": 188}, {"index": 2, "subkeyword": "분야", "cooccur_num": 165}, {"index": 3, "subkeyword": "연구", "cooccur_num": 141}, {"index": 4, "subkeyword": "결과", "cooccur_num": 91}, {"index": 5, "subkeyword": "협력", "cooccur_num": 82}, {"index": 6, "subkeyword": "교수", "cooccur_num": 54}, {"index": 7, "subkeyword": "기구", "cooccur_num": 53}, {"index": 8, "subkeyword": "센터", "cooccur_num": 51}, {"index": 9, "subkeyword": "과학", "cooccur_num": 48}, {"index": 10, "subkeyword": "기술", "cooccur_num": 45}], "similar": [{"index": 1, "subkeyword": "학술", "cooccur_num": 0.9302809238433838}, {"index": 2, "subkeyword": "저작", "cooccur_num": 0.8849129676818848}, {"index": 3, "subkeyword": "학술지", "cooccur_num": 0.88116455078125}, {"index": 4, "subkeyword": "바이오테크놀로지", "cooccur_num": 0.8787059187889099}, {"index": 5, "subkeyword": "권위자", "cooccur_num": 0.871437668800354}, {"index": 6, "subkeyword": "기능올림픽", "cooccur_num": 0.8706650137901306}, {"index": 7, "subkeyword": "심포지엄", "cooccur_num": 0.8672137260437012}, {"index": 8, "subkeyword": "학회", "cooccur_num": 0.8654323220252991}, {"index": 9, "subkeyword": "생명공학", "cooccur_num": 0.8610752820968628}, {"index": 10, "subkeyword": "세포생물학", "cooccur_num": 0.860525369644165}]}, {"keyword": "문화", "score": 1127, "cooccur": [{"index": 1, "subkeyword": "한국", "cooccur_num": 97}, {"index": 2, "subkeyword": "기술", "cooccur_num": 82}, {"index": 3, "subkeyword": "예술", "cooccur_num": 80}, {"index": 4, "subkeyword": "산업", "cooccur_num": 72}, {"index": 5, "subkeyword": "과학", "cooccur_num": 58}, {"index": 6, "subkeyword": "콘텐츠", "cooccur_num": 57}, {"index": 7, "subkeyword": "서울", "cooccur_num": 50}, {"index": 8, "subkeyword": "교수", "cooccur_num": 49}, {"index": 9, "subkeyword": "체육관", "cooccur_num": 47}, {"index": 10, "subkeyword": "교육", "cooccur_num": 47}], "similar": [{"index": 1, "subkeyword": "미래", "cooccur_num": 0.8686543703079224}, {"index": 2, "subkeyword": "융성", "cooccur_num": 0.8663699626922607}, {"index": 3, "subkeyword": "도시", "cooccur_num": 0.8657976984977722}, {"index": 4, "subkeyword": "예술", "cooccur_num": 0.8536993265151978}, {"index": 5, "subkeyword": "복지", "cooccur_num": 0.8332810401916504}, {"index": 6, "subkeyword": "대한민국", "cooccur_num": 0.8294618725776672}, {"index": 7, "subkeyword": "관광부", "cooccur_num": 0.8255606889724731}, {"index": 8, "subkeyword": "창조", "cooccur_num": 0.8243271708488464}, {"index": 9, "subkeyword": "경제", "cooccur_num": 0.8210126757621765}, {"index": 10, "subkeyword": "정동채", "cooccur_num": 0.8209845423698425}]}, {"keyword": "사장", "score": 1120, "cooccur": [{"index": 1, "subkeyword": "삼성", "cooccur_num": 161}, {"index": 2, "subkeyword": "부", "cooccur_num": 154}, {"index": 3, "subkeyword": "승진", "cooccur_num": 70}, {"index": 4, "subkeyword": "한국", "cooccur_num": 68}, {"index": 5, "subkeyword": "장", "cooccur_num": 62}, {"index": 6, "subkeyword": "맡다", "cooccur_num": 57}, {"index": 7, "subkeyword": "김", "cooccur_num": 55}, {"index": 8, "subkeyword": "윤송", "cooccur_num": 54}, {"index": 9, "subkeyword": "사업", "cooccur_num": 54}, {"index": 10, "subkeyword": "씨", "cooccur_num": 50}], "similar": [{"index": 1, "subkeyword": "넥스", "cooccur_num": 0.9222756028175354}, {"index": 2, "subkeyword": "부회장", "cooccur_num": 0.9164049625396729}, {"index": 3, "subkeyword": "엔씨소프트", "cooccur_num": 0.9127745628356934}, {"index": 4, "subkeyword": "대표이사", "cooccur_num": 0.9079344868659973}, {"index": 5, "subkeyword": "한화", "cooccur_num": 0.9067457318305969}, {"index": 6, "subkeyword": "텔레콤", "cooccur_num": 0.9036879539489746}, {"index": 7, "subkeyword": "상무", "cooccur_num": 0.888414740562439}, {"index": 8, "subkeyword": "윤송", "cooccur_num": 0.8882685899734497}, {"index": 9, "subkeyword": "증권", "cooccur_num": 0.8874143362045288}, {"index": 10, "subkeyword": "대표", "cooccur_num": 0.8869072794914246}]}]